<?xml version="1.0" encoding="UTF-8"?>

<!-- generated on 07/26/20 08:24:38 by Eclipse SUMO Version 1.5.0
<configuration xmlns:xsi="http://www.w3.org/2001/XMLSchema-instance" xsi:noNamespaceSchemaLocation="http://sumo.dlr.de/xsd/sumoConfiguration.xsd">

    <input>
        <net-file value="./mapas/3.net.xml"/>
        <route-files value="./mapas/rota.rou.xml"/>
    </input>

    <output>
        <tripinfo-output value="./output/3.net.xml_29_1389.out.xml"/>
    </output>

    <report>
        <verbose value="true"/>
        <log value="logfile.txt"/>
        <duration-log.statistics value="true"/>
    </report>

    <emissions>
        <device.emissions.probability value="1"/>
    </emissions>

    <traci_server>
        <remote-port value="52297"/>
    </traci_server>

</configuration>
-->

<tripinfos xmlns:xsi="http://www.w3.org/2001/XMLSchema-instance" xsi:noNamespaceSchemaLocation="http://sumo.dlr.de/xsd/tripinfo_file.xsd">
    <tripinfo id="caminhao" depart="0.00" departLane="A0B0_0" departPos="5.10" departSpeed="0.00" departDelay="0.00" arrival="197.00" arrivalLane="S0T0_0" arrivalPos="67.12" arrivalSpeed="11.06" duration="197.00" routeLength="2148.05" waitingTime="0.00" waitingCount="0" stopTime="0.00" timeLoss="50.38" rerouteNo="0" devices="tripinfo_caminhao emissions_caminhao" vType="DEFAULT_VEHTYPE@caminhao" speedFactor="1.06" vaporized="">
        <emissions CO_abs="2261.127697" CO2_abs="1464206.854182" HC_abs="0" PMx_abs="283.833869" NOx_abs="12939.736644" fuel_abs="620.729723" electricity_abs="0"/>
    </tripinfo>
</tripinfos>
