<?xml version="1.0" encoding="UTF-8"?>

<!-- generated on 07/26/20 14:07:57 by Eclipse SUMO Version 1.5.0
<configuration xmlns:xsi="http://www.w3.org/2001/XMLSchema-instance" xsi:noNamespaceSchemaLocation="http://sumo.dlr.de/xsd/sumoConfiguration.xsd">

    <input>
        <net-file value="./mapas/5.net.xml"/>
        <route-files value="./mapas/rota.rou.xml"/>
    </input>

    <output>
        <tripinfo-output value="./output/5.net.xml_37_1741.out.xml"/>
    </output>

    <report>
        <verbose value="true"/>
        <log value="logfile.txt"/>
        <duration-log.statistics value="true"/>
    </report>

    <emissions>
        <device.emissions.probability value="1"/>
    </emissions>

    <traci_server>
        <remote-port value="61822"/>
    </traci_server>

</configuration>
-->

<tripinfos xmlns:xsi="http://www.w3.org/2001/XMLSchema-instance" xsi:noNamespaceSchemaLocation="http://sumo.dlr.de/xsd/tripinfo_file.xsd">
    <tripinfo id="caminhao" depart="0.00" departLane="A0B0_0" departPos="5.10" departSpeed="0.00" departDelay="0.00" arrival="163.00" arrivalLane="S0T0_0" arrivalPos="92.80" arrivalSpeed="14.25" duration="163.00" routeLength="2283.64" waitingTime="0.00" waitingCount="0" stopTime="0.00" timeLoss="7.50" rerouteNo="0" devices="tripinfo_caminhao emissions_caminhao" vType="DEFAULT_VEHTYPE@caminhao" speedFactor="1.06" vaporized="">
        <emissions CO_abs="2184.807919" CO2_abs="1502434.486162" HC_abs="0" PMx_abs="265.100679" NOx_abs="12700.006114" fuel_abs="636.937884" electricity_abs="0"/>
    </tripinfo>
</tripinfos>
