<?xml version="1.0" encoding="UTF-8"?>

<!-- generated on 08/06/20 06:36:20 by Eclipse SUMO Version 1.6.0
<configuration xmlns:xsi="http://www.w3.org/2001/XMLSchema-instance" xsi:noNamespaceSchemaLocation="http://sumo.dlr.de/xsd/sumoConfiguration.xsd">

    <input>
        <net-file value="./mapas/super.net.xml"/>
        <route-files value="./mapas/rota.rou.xml"/>
    </input>

    <output>
        <tripinfo-output value="./output/super.net.xml_180_3256.out.xml"/>
    </output>

    <report>
        <verbose value="true"/>
        <log value="logfile.txt"/>
        <duration-log.statistics value="true"/>
    </report>

    <emissions>
        <device.emissions.probability value="1"/>
    </emissions>

    <traci_server>
        <remote-port value="59757"/>
    </traci_server>

</configuration>
-->

<tripinfos xmlns:xsi="http://www.w3.org/2001/XMLSchema-instance" xsi:noNamespaceSchemaLocation="http://sumo.dlr.de/xsd/tripinfo_file.xsd">
    <tripinfo id="caminhao" depart="0.00" departLane="AA0AB0_0" departPos="5.10" departSpeed="0.00" departDelay="0.00" arrival="1070.00" arrivalLane="LN0LO0_0" arrivalPos="89.66" arrivalSpeed="28.21" duration="1070.00" routeLength="30146.24" waitingTime="0.00" waitingCount="0" stopTime="0.00" timeLoss="65.07" rerouteNo="0" devices="tripinfo_caminhao emissions_caminhao" vType="DEFAULT_VEHTYPE@caminhao" speedFactor="1.06" vaporized="">
        <emissions CO_abs="139534.143715" CO2_abs="4871100.918341" HC_abs="768.559393" PMx_abs="231.962920" NOx_abs="2193.523697" fuel_abs="13401.973031" electricity_abs="0"/>
    </tripinfo>
</tripinfos>